nonebot/adapters/minecraft/__init__.py
nonebot/adapters/minecraft/adapter.py
nonebot/adapters/minecraft/config.py
nonebot/adapters/minecraft/event.py
nonebot/adapters/minecraft/logger.py
nonebot/adapters/minecraft/message.py
nonebot/adapters/minecraft/server.py
nonebot/adapters/minecraft/utils.py
nonebot_adapter_minecraft_server-1.3.3.dist-info/LICENSE
nonebot_adapter_minecraft_server-1.3.3.dist-info/METADATA
nonebot_adapter_minecraft_server-1.3.3.dist-info/WHEEL
nonebot_adapter_minecraft_server-1.3.3.dist-info/RECORD
