Metadata-Version: 2.1
Name: nonebot_adapter_minecraft_server
Version: 1.3.3
Summary: Minecraft 服务器连接 NoneBot2 的适配器。
License: GPL3
Author: LonelySail
Author-email: xiaocaicai_email@sina.com
Requires-Python: >=3.9,<4.0
Classifier: License :: Other/Proprietary License
Classifier: Programming Language :: Python :: 3
Classifier: Programming Language :: Python :: 3.9
Classifier: Programming Language :: Python :: 3.10
Classifier: Programming Language :: Python :: 3.11
Classifier: Programming Language :: Python :: 3.12
Requires-Dist: nonebot2 (>=2.2.0,<3.0.0)
